moksh_orchestrator/__init__.py
moksh_orchestrator/framework/__init__.py
moksh_orchestrator/framework/apis/__init__.py
moksh_orchestrator/framework/apis/dataset.py
moksh_orchestrator/framework/apis/exception_handler.py
moksh_orchestrator/framework/apis/execution_context.py
moksh_orchestrator/framework/apis/orchestrator.py
moksh_orchestrator/framework/apis/routable_step.py
moksh_orchestrator/framework/apis/step.py
moksh_orchestrator/framework/config/__init__.py
moksh_orchestrator/framework/config/task-schema.yaml
moksh_orchestrator/framework/config/validators/__init__.py
moksh_orchestrator/framework/config/validators/orchestrator_type_validator.py
moksh_orchestrator/framework/config/validators/step_type_validator.py
moksh_orchestrator/framework/config/validators/validate_pipeline.py
moksh_orchestrator/framework/impl/__init__.py
moksh_orchestrator/framework/impl/dataset_impl.py
moksh_orchestrator/framework/impl/exeuction_context_impl.py
moksh_orchestrator/framework/impl/orchestrator_impl.py
moksh_orchestrator/framework/impl/step_impl.py
moksh_orchestrator/framework/impl/steps.py
moksh_orchestrator/framework/moksh.py
moksh_orchestrator/framework/parallel/__init__.py
moksh_orchestrator/framework/parallel/dask-workers.yaml
moksh_orchestrator/framework/parallel/parallel_executor.py
moksh_orchestrator/framework/utils/__init__.py
moksh_orchestrator/framework/utils/class_utils.py
moksh_orchestrator/framework/utils/file_utils.py
moksh_orchestrator/framework/utils/interface_utils.py
moksh_orchestrator/framework/utils/module_loader.py
moksh_orchestrator/logging/DelMe.py
moksh_orchestrator/logging/__init__.py
moksh_orchestrator/logging/moksh_logger.py
moksh_orchestrator-0.2.1.dist-info/WHEEL
moksh_orchestrator-0.2.1.dist-info/METADATA
moksh_orchestrator-0.2.1.dist-info/RECORD
