Metadata-Version: 2.1
Name: moksh-orchestrator
Version: 0.2.1
Summary: 
Author: gmalho
Author-email: gaurav.malhotra@nike.com
Requires-Python: >=3.8,<4.0
Classifier: Programming Language :: Python :: 3
Classifier: Programming Language :: Python :: 3.8
Requires-Dist: Zope (>=4.4.3,<5.0.0)
Requires-Dist: dask (>=2.18.1,<3.0.0)
Requires-Dist: dask-kubernetes (>=0.10.1,<0.11.0)
Requires-Dist: dpath (>=2.0.1,<3.0.0)
Requires-Dist: mypy (>=0.780,<0.781)
Requires-Dist: pinject (>=0.14.1,<0.15.0)
Requires-Dist: python-interface (>=1.6.0,<2.0.0)
Requires-Dist: pyyaml (>=5.3.1,<6.0.0)
Requires-Dist: ruamel.yaml (>=0.16.10,<0.17.0)
Requires-Dist: yamale (>=2.1.0,<3.0.0)
